text_viewer/__init__.py
text_viewer/alphabet.py
text_viewer/operations.py
text_viewer_girvel-0.0.4.dist-info/METADATA
text_viewer_girvel-0.0.4.dist-info/WHEEL
text_viewer_girvel-0.0.4.dist-info/top_level.txt
text_viewer_girvel-0.0.4.dist-info/RECORD
