Metadata-Version: 2.1
Name: text-viewer-girvel
Version: 0.0.4
Summary: Package for displaying stuff in console
Home-page: https://github.com/girvel/text_actions
Author: girvel
Author-email: widauka@yandex.ru
License: UNKNOWN
Platform: UNKNOWN
Classifier: Programming Language :: Python :: 3
Classifier: License :: OSI Approved :: MIT License
Classifier: Operating System :: OS Independent
Requires-Python: >=3.6
